{
    "manifestVersion": 1,
    "id": "rp-build-release-azurepolicy",
    "name": "Azure Policy and Governance Pipelines Tasks",
    "version": "2.0.4",
    "publisher": "RazorSPoint",
    "targets": [{
        "id": "Microsoft.VisualStudio.Services"
    }],
    "description": "Tasks for Builds and Releases related to Governance Topics.",
    "categories": [
        "Azure Pipelines"
    ],
    "galleryFlags": [
        "Public"
    ],
    "tags": [
        "Azure Policy","Initiative","Policy Set","Management Groups",
        "Governance", "Deployment","Compliance", "RazorSPoint"],
    "icons": {
        "default": "Images/Icon128x128.png",
        "large": "Images/Icon512x512.png"
    },
    "content": {
        "details": {
            "path": "overview.md"
        },
        "license": {
            "path": "eula.md"
        },
        "privacypolicy": {
            "path":"privacy.md"
        }
    },
    "links": {        
        "getstarted": {
            "uri": "https://razorspoint.github.io/azure-devops-azure-policy-extension/"
        },
        "learn": {
            "uri": "https://docs.microsoft.com/en-us/azure/governance/policy/overview"
        },
        "issues": { 
            "uri": "https://github.com/RazorSPoint/azure-devops-azure-policy-extension/issues"
        },
        "support": {
            "uri": "https://github.com/RazorSPoint/azure-devops-azure-policy-extension/issues"
        }
    },
    "repository": {
        "type": "git",
        "uri": "https://github.com/RazorSPoint/azure-devops-azure-policy-extension"
    },
    "badges": [
        {
            "href": "https://dev.azure.com/razorspoint/RP_Build-Release-AzurePolicy/_build/latest?definitionId=19",
            "uri": "https://dev.azure.com/razorspoint/RP_Build-Release-AzurePolicy/_apis/build/status/RazorSPoint.azure-devops-azure-policy-extension?branchName=master&stageName=Build&jobName=Build%20Extension&label=Build",
            "description": "Build"
        },
        {
            "href": "https://dev.azure.com/razorspoint/RP_Build-Release-AzurePolicy/_build/latest?definitionId=19",
            "uri": "https://img.shields.io/azure-devops/tests/razorspoint/RP_Build-Release-AzurePolicy/19?label=unit%20tests",
            "description": "Passed Unit Tests"
        },
        {
            "href": "https://dev.azure.com/razorspoint/RP_Build-Release-AzurePolicy/_build/latest?definitionId=19",
            "uri": "https://img.shields.io/azure-devops/coverage/razorspoint/RP_Build-Release-AzurePolicy/19?label=code%20coverage",
            "description": "Code Coverage"
        },
        {
            "href": "https://dev.azure.com/RazorSPoint/RP_Build-Release-AzurePolicy/_build/latest?definitionId=19&branchName=master",
            "uri": "https://dev.azure.com/razorspoint/RP_Build-Release-AzurePolicy/_apis/build/status/RazorSPoint.azure-devops-azure-policy-extension?branchName=master&stageName=Staging&jobName=Test%20Release&label=Test%20Release",
            "description": "Test Release"
        },
        {
            "href": "https://dev.azure.com/RazorSPoint/RP_Build-Release-AzurePolicy/_build/latest?definitionId=19&branchName=master",
            "uri": "https://dev.azure.com/razorspoint/RP_Build-Release-AzurePolicy/_apis/build/status/RazorSPoint.azure-devops-azure-policy-extension?branchName=master&stageName=Production&jobName=Public%20Marketplace&label=Live%20Release",
            "description": "Live Release"
        }
    ],
    "screenshots": [{
            "path": "Images/Preview01.png"
        },
        {
            "path": "Images/Preview02.png"
        },
        {
            "path": "Images/Preview03.png"
        },
        {
            "path": "Images/Preview04.png"
        }
    ],
    "branding": {
        "color": "rgb(50,49,48)",
        "theme": "dark"
    },
    "scopes": [
        "vso.build_execute"
    ],
    "files": [
        {
            "path": "AzurePolicy"
        },
        {
            "path": "AzureInitiative"
        },
        {
            "path": "Images",
            "addressable": true
        }
    ],
    "contributions": [
        {
            "id": "RP-AzurePolicy",
            "type": "ms.vss-distributed-task.task",
            "targets": [
                "ms.vss-distributed-task.tasks"
            ],
            "properties": {
                "name": "AzurePolicy"
            }
        },
        {
            "id": "RP-AzureInitiative",
            "type": "ms.vss-distributed-task.task",
            "targets": [
                "ms.vss-distributed-task.tasks"
            ],
            "properties": {
                "name": "AzureInitiative"
            }
        }   
    ]
}
